MANIFEST.in
README.rst
setup.cfg
setup.py
floyd/__init__.py
floyd/constants.py
floyd/date_utils.py
floyd/exceptions.py
floyd/log.py
floyd/main.py
floyd/cli/__init__.py
floyd/cli/auth.py
floyd/cli/data.py
floyd/cli/data_upload_utils.py
floyd/cli/default_floyd.yml
floyd/cli/experiment.py
floyd/cli/run.py
floyd/cli/utils.py
floyd/cli/version.py
floyd/client/__init__.py
floyd/client/auth.py
floyd/client/base.py
floyd/client/common.py
floyd/client/data.py
floyd/client/dataset.py
floyd/client/env.py
floyd/client/experiment.py
floyd/client/files.py
floyd/client/module.py
floyd/client/project.py
floyd/client/resource.py
floyd/client/task_instance.py
floyd/client/tus_data.py
floyd/client/version.py
floyd/development/__init__.py
floyd/development/dev.py
floyd/development/local.py
floyd/manager/__init__.py
floyd/manager/auth_config.py
floyd/manager/data_config.py
floyd/manager/experiment_config.py
floyd/manager/floyd_ignore.py
floyd/manager/login.py
floyd/model/__init__.py
floyd/model/access_token.py
floyd/model/base.py
floyd/model/credentials.py
floyd/model/data.py
floyd/model/dataset.py
floyd/model/env.py
floyd/model/experiment.py
floyd/model/experiment_config.py
floyd/model/module.py
floyd/model/project.py
floyd/model/resource.py
floyd/model/task_instance.py
floyd/model/user.py
floyd/model/version.py
floyd_cli.egg-info/PKG-INFO
floyd_cli.egg-info/SOURCES.txt
floyd_cli.egg-info/dependency_links.txt
floyd_cli.egg-info/entry_points.txt
floyd_cli.egg-info/not-zip-safe
floyd_cli.egg-info/requires.txt
floyd_cli.egg-info/top_level.txt