Metadata-Version: 1.0
Name: floyd-cli
Version: 0.11.12
Summary: Command line tool for Floyd
Home-page: https://github.com/floydhub/floyd-cli
Author: Floyd Labs Inc.
Author-email: support@floydhub.com
License: UNKNOWN
Keywords: floyd
Platform: UNKNOWN
